odoo/addons/account_invoice_import_simple_pdf/README.rst
odoo/addons/account_invoice_import_simple_pdf/__init__.py
odoo/addons/account_invoice_import_simple_pdf/__manifest__.py
odoo/addons/account_invoice_import_simple_pdf/demo/demo_data.xml
odoo/addons/account_invoice_import_simple_pdf/i18n/account_invoice_import_simple_pdf.pot
odoo/addons/account_invoice_import_simple_pdf/i18n/es.po
odoo/addons/account_invoice_import_simple_pdf/i18n/fr.po
odoo/addons/account_invoice_import_simple_pdf/migrations/14.0.1.0.1/pre-migration.py
odoo/addons/account_invoice_import_simple_pdf/models/__init__.py
odoo/addons/account_invoice_import_simple_pdf/models/account_invoice_import_simple_pdf_fields.py
odoo/addons/account_invoice_import_simple_pdf/models/account_invoice_import_simple_pdf_invoice_number.py
odoo/addons/account_invoice_import_simple_pdf/models/res_partner.py
odoo/addons/account_invoice_import_simple_pdf/readme/CONFIGURE.rst
odoo/addons/account_invoice_import_simple_pdf/readme/CONTRIBUTORS.rst
odoo/addons/account_invoice_import_simple_pdf/readme/DESCRIPTION.rst
odoo/addons/account_invoice_import_simple_pdf/readme/INSTALL.rst
odoo/addons/account_invoice_import_simple_pdf/security/ir.model.access.csv
odoo/addons/account_invoice_import_simple_pdf/static/description/icon.png
odoo/addons/account_invoice_import_simple_pdf/static/description/index.html
odoo/addons/account_invoice_import_simple_pdf/tests/__init__.py
odoo/addons/account_invoice_import_simple_pdf/tests/test_invoice_import.py
odoo/addons/account_invoice_import_simple_pdf/tests/pdf/akretion_france-test.pdf
odoo/addons/account_invoice_import_simple_pdf/tests/pdf/bouygues_telecom-test.pdf
odoo/addons/account_invoice_import_simple_pdf/views/account_invoice_import_simple_pdf_fields.xml
odoo/addons/account_invoice_import_simple_pdf/views/account_invoice_import_simple_pdf_invoice_number.xml
odoo/addons/account_invoice_import_simple_pdf/views/res_partner.xml
odoo/addons/account_invoice_import_simple_pdf/wizard/__init__.py
odoo14_addon_account_invoice_import_simple_pdf-14.0.4.1.0.dist-info/METADATA
odoo14_addon_account_invoice_import_simple_pdf-14.0.4.1.0.dist-info/WHEEL
odoo14_addon_account_invoice_import_simple_pdf-14.0.4.1.0.dist-info/top_level.txt
odoo14_addon_account_invoice_import_simple_pdf-14.0.4.1.0.dist-info/RECORD
