Metadata-Version: 2.1
Name: odoo14-addon-account_invoice_import_simple_pdf
Version: 14.0.4.1.0
Summary: Import simple PDF vendor bills
Home-page: https://github.com/OCA/edi
Author: Akretion,Odoo Community Association (OCA)
Author-email: support@odoo-community.org
License: AGPL-3
Classifier: Programming Language :: Python
Classifier: Framework :: Odoo
Classifier: Framework :: Odoo :: 14.0
Classifier: License :: OSI Approved :: GNU Affero General Public License v3
Requires-Python: >=3.6
Requires-Dist: dateparser
Requires-Dist: odoo14-addon-account-invoice-import
Requires-Dist: odoo <14.1dev,>=14.0a
Requires-Dist: pypdf <5.0,>=3.1.0
Requires-Dist: regex
